Metadata-Version: 2.1
Name: skyplane-nightly
Version: 0.3.2.dev202307072345
Summary: Skyplane efficiently transports data between cloud regions and providers.
Home-page: https://skyplane.org/
License: Apache-2.0
Author: Skyplane authors
Author-email: skyplaneproject@gmail.com
Requires-Python: >=3.7.1,<3.12
Classifier: License :: OSI Approved :: Apache Software License
Classifier: Programming Language :: Python :: 3
Classifier: Programming Language :: Python :: 3.8
Classifier: Programming Language :: Python :: 3.9
Classifier: Programming Language :: Python :: 3.10
Classifier: Programming Language :: Python :: 3.11
Provides-Extra: all
Provides-Extra: aws
Provides-Extra: azure
Provides-Extra: gateway
Provides-Extra: gcp
Provides-Extra: ibm
Provides-Extra: solver
Requires-Dist: azure-identity (>=1.0.0) ; extra == "azure" or extra == "all"
Requires-Dist: azure-mgmt-authorization (>=1.0.0) ; extra == "azure" or extra == "all"
Requires-Dist: azure-mgmt-compute (>=24.0.0) ; extra == "azure" or extra == "all"
Requires-Dist: azure-mgmt-network (>=10.0.0) ; extra == "azure" or extra == "all"
Requires-Dist: azure-mgmt-quota (>=1.1.0b3) ; extra == "azure"
Requires-Dist: azure-mgmt-resource (>=11.0.0) ; extra == "azure" or extra == "all"
Requires-Dist: azure-mgmt-storage (>=11.0.0) ; extra == "azure" or extra == "all"
Requires-Dist: azure-mgmt-subscription (>=1.0.0) ; extra == "azure" or extra == "all"
Requires-Dist: azure-storage-blob (>=12.0.0) ; extra == "azure" or extra == "all"
Requires-Dist: boto3 (>=1.16.0) ; extra == "aws" or extra == "all"
Requires-Dist: cachetools (>=4.1.0)
Requires-Dist: cryptography (>=1.4.0)
Requires-Dist: cvxpy (>=1.1.0) ; extra == "solver"
Requires-Dist: flask (>=2.1.2,<3.0.0) ; extra == "gateway"
Requires-Dist: google-api-python-client (>=2.0.2) ; extra == "gcp" or extra == "all"
Requires-Dist: google-auth (>=2.0.0) ; extra == "gcp" or extra == "all"
Requires-Dist: google-cloud-compute (>=1.0.0) ; extra == "gcp" or extra == "all"
Requires-Dist: google-cloud-dataproc (>=5.4.0,<6.0.0)
Requires-Dist: google-cloud-storage (>=1.30.0) ; extra == "gcp" or extra == "all"
Requires-Dist: graphviz (>=0.15) ; extra == "solver"
Requires-Dist: ibm-cloud-sdk-core (>=3.16.2) ; extra == "ibm" or extra == "all"
Requires-Dist: ibm-cos-sdk (>=2.12.2) ; extra == "ibm" or extra == "all"
Requires-Dist: ibm-cos-sdk-core (>=2.12.2)
Requires-Dist: ibm-cos-sdk-s3transfer (>=2.12.2)
Requires-Dist: ibm-vpc (>=0.15.0) ; extra == "ibm" or extra == "all"
Requires-Dist: lz4 (>=4.0.0,<5.0.0) ; extra == "gateway"
Requires-Dist: matplotlib (>=3.0.0) ; extra == "solver"
Requires-Dist: numpy (>=1.19.0) ; extra == "solver"
Requires-Dist: pandas (>=1.0.0)
Requires-Dist: paramiko (>=2.7.2)
Requires-Dist: pyarrow (>=10.0.1,<11.0.0)
Requires-Dist: pynacl (>=1.5.0,<2.0.0) ; extra == "gateway"
Requires-Dist: pyopenssl (>=22.0.0,<23.0.0) ; extra == "gateway"
Requires-Dist: questionary (>=1.8.0)
Requires-Dist: requests (>=2.23.0)
Requires-Dist: rich (>=9.0.0)
Requires-Dist: sshtunnel (>=0.3.0)
Requires-Dist: typer (>=0.4.0)
Requires-Dist: werkzeug (>=2.1.2,<3.0.0) ; extra == "gateway"
Project-URL: Documentation, https://skyplane.org/
Project-URL: Repository, https://github.com/skyplane-project/skyplane
